intermittent_levy/__init__.py
intermittent_levy/classification.py
intermittent_levy/moments.py
intermittent_levy/optimization.py
intermittent_levy/processes.py
intermittent_levy/utils.py
intermittent_levy/tests/__init__.py
intermittent_levy/tests/test_classification.py
intermittent_levy/tests/test_moments.py
intermittent_levy/tests/test_optimization.py
intermittent_levy/tests/test_processes.py
InterLevPy-0.0.1.dist-info/LICENSE
InterLevPy-0.0.1.dist-info/METADATA
InterLevPy-0.0.1.dist-info/WHEEL
InterLevPy-0.0.1.dist-info/top_level.txt
InterLevPy-0.0.1.dist-info/RECORD
