Metadata-Version: 2.1
Name: InterLevPy
Version: 0.0.1
Summary: A Python toolkit for simulating intermittent processes and Levy flights.
Home-page: https://github.com/shailendrabhandari/IntLevy-Processes
Author: Shailendra Bhandari
Author-email: shailendra.bhandari@oslomet.no
Classifier: Programming Language :: Python :: 3
Classifier: License :: OSI Approved :: MIT License
Classifier: Operating System :: OS Independent
Requires-Python: >=3.6
License-File: LICENSE
